airflow/providers/mysql/__init__.py
airflow/providers/mysql/example_dags/__init__.py
airflow/providers/mysql/example_dags/example_mysql.py
airflow/providers/mysql/hooks/__init__.py
airflow/providers/mysql/hooks/mysql.py
airflow/providers/mysql/operators/__init__.py
airflow/providers/mysql/operators/mysql.py
airflow/providers/mysql/transfers/__init__.py
airflow/providers/mysql/transfers/presto_to_mysql.py
airflow/providers/mysql/transfers/s3_to_mysql.py
airflow/providers/mysql/transfers/vertica_to_mysql.py
apache_airflow_backport_providers_mysql-2021.3.3.dist-info/LICENSE
apache_airflow_backport_providers_mysql-2021.3.3.dist-info/METADATA
apache_airflow_backport_providers_mysql-2021.3.3.dist-info/NOTICE
apache_airflow_backport_providers_mysql-2021.3.3.dist-info/WHEEL
apache_airflow_backport_providers_mysql-2021.3.3.dist-info/top_level.txt
apache_airflow_backport_providers_mysql-2021.3.3.dist-info/RECORD
