Metadata-Version: 2.1
Name: apache-airflow-backport-providers-mysql
Version: 2021.3.3
Summary: Backport provider package apache-airflow-backport-providers-mysql for Apache Airflow
Home-page: https://airflow.apache.org/
Author: Apache Software Foundation
Author-email: dev@airflow.apache.org
License: Apache License 2.0
Download-URL: https://archive.apache.org/dist/airflow/backport-providers
Project-URL: Documentation, https://airflow.apache.org/docs/
Project-URL: Bug Tracker, https://github.com/apache/airflow/issues
Project-URL: Source Code, https://github.com/apache/airflow
Platform: UNKNOWN
Classifier: Development Status :: 5 - Production/Stable
Classifier: Environment :: Console
Classifier: Environment :: Web Environment
Classifier: Intended Audience :: Developers
Classifier: Intended Audience :: System Administrators
Classifier: License :: OSI Approved :: Apache Software License
Classifier: Programming Language :: Python :: 3.6
Classifier: Programming Language :: Python :: 3.7
Classifier: Programming Language :: Python :: 3.8
Classifier: Topic :: System :: Monitoring
Requires-Python: ~=3.6
Requires-Dist: apache-airflow (~=1.10)
Requires-Dist: mysql-connector-python (<=8.0.22,>=8.0.11)
Requires-Dist: mysqlclient (<1.4,>=1.3.6)
Provides-Extra: amazon
Requires-Dist: apache-airflow-backport-providers-amazon ; extra == 'amazon'
Provides-Extra: presto
Requires-Dist: apache-airflow-backport-providers-presto ; extra == 'presto'
Provides-Extra: vertica
Requires-Dist: apache-airflow-backport-providers-vertica ; extra == 'vertica'
